SelfBotClient/__init__.py
SelfBotClient/__main__.py
SelfBotClient/client.py
SelfBotClient/enums.py
SelfBotClient/errors.py
SelfBotClient/http.py
SelfBotClient/logger.py
SelfBotClient/permissionbuilder.py
SelfBotClient/tasks.py
SelfBotClient/typings.py
SelfBotClient/user.py
selfbotclient-1.1.2.dist-info/METADATA
selfbotclient-1.1.2.dist-info/WHEEL
selfbotclient-1.1.2.dist-info/top_level.txt
selfbotclient-1.1.2.dist-info/RECORD
