Metadata-Version: 2.1
Name: selfbotclient
Version: 1.1.2
Summary: Library that will allow you to manage selfbots
Author: xXenvy
Author-email: <xpimepk01@gmail.com>
Keywords: python,requests,discord selfbot,selfbot,discord.py,aiohttp
Classifier: Development Status :: 1 - Planning
Classifier: Intended Audience :: Developers
Classifier: Programming Language :: Python :: 3
Classifier: Operating System :: Unix
Classifier: Operating System :: MacOS :: MacOS X
Classifier: Operating System :: Microsoft :: Windows
Requires-Dist: colorlog
Requires-Dist: aiohttp
